{
    "categoryItemList": [
        {
            "category": {
                "bannerUrl": "http://yanxuan.nosdn.127.net/da884ff3b9e9d5276986c99e85722461.png",
                "frontDesc": "海外供应商直供，零关税、零风险、即时达",
                "frontName": "来自日本制造的好物",
                "iconUrl": "",
                "id": 1011002,
                "imgUrl": "",
                "level": "L2",
                "name": "日本",
                "showIndex": 1,
                "subCateList": [],
                "superCategoryId": 0
            },
            "itemList": [
                {
                    "attrList": [],
                    "colorNum": 0,
                    "comments": [],
                    "gradientPrice": null,
                    "hdrkDetailVOList": [],
                    "id": 1086045,
                    "issueList": [],
                    "itemDetail": null,
                    "limitedFlag": false,
                    "listPicUrl": "",
                    "name": "日本制造 天然樱花香皂",
                    "newItemFlag": true,
                    "pieceNum": 0,
                    "pieceUnitDesc": "件",
                    "primaryPicUrl": "http://yanxuan.nosdn.127.net/132684e2db93f6722b138eaf87a4a435.png",
                    "primarySkuId": 1091148,
                    "primarySkuPreSellPrice": 0,
                    "primarySkuPreSellStatus": 0,
                    "rank": 1,
                    "reportPicList": [],
                    "retailPrice": 19,
                    "sellVolume": 7347,
                    "seoTitle": "",
                    "simpleDesc": "高颜值樱花泡泡皂，沐浴日本樱花文化",
                    "skuList": [],
                    "skuMap": null,
                    "skuSpecList": [],
                    "soldOut": false,
                    "status": 2,
                    "tagList": [],
                    "underShelf": false,
                    "unitPrice": 0
                },
                {
                    "attrList": [],
                    "colorNum": 0,
                    "comments": [],
                    "gradientPrice": null,
                    "hdrkDetailVOList": [],
                    "id": 1088011,
                    "issueList": [],
                    "itemDetail": null,
                    "limitedFlag": false,
                    "listPicUrl": "",
                    "name": "日本制造 南部铁器风炒锅30cm",
                    "newItemFlag": false,
                    "pieceNum": 0,
                    "pieceUnitDesc": "件",
                    "primaryPicUrl": "http://yanxuan.nosdn.127.net/421abc2cba885181e3e8312a7a0155be.png",
                    "primarySkuId": 1093026,
                    "primarySkuPreSellPrice": 0,
                    "primarySkuPreSellStatus": 0,
                    "rank": 2,
                    "reportPicList": [],
                    "retailPrice": 359,
                    "sellVolume": 19,
                    "seoTitle": "",
                    "simpleDesc": "日本百年铁器文化，还原品质生活",
                    "skuList": [],
                    "skuMap": null,
                    "skuSpecList": [],
                    "soldOut": false,
                    "status": 2,
                    "tagList": [],
                    "underShelf": false,
                    "unitPrice": 0
                },
                {
                    "attrList": [],
                    "colorNum": 0,
                    "comments": [],
                    "gradientPrice": null,
                    "hdrkDetailVOList": [],
                    "id": 1091000,
                    "issueList": [],
                    "itemDetail": null,
                    "limitedFlag": false,
                    "listPicUrl": "",
                    "name": "日本制造 和风侘寂茶碗",
                    "newItemFlag": true,
                    "pieceNum": 0,
                    "pieceUnitDesc": "件",
                    "primaryPicUrl": "http://yanxuan.nosdn.127.net/7129bf96a8beb0f9ebfd36793a5b54c4.png",
                    "primarySkuId": 1096001,
                    "primarySkuPreSellPrice": 0,
                    "primarySkuPreSellStatus": 0,
                    "rank": 3,
                    "reportPicList": [],
                    "retailPrice": 69,
                    "sellVolume": 1616,
                    "seoTitle": "",
                    "simpleDesc": "日式侘寂美学，传承茶道手作美瓷",
                    "skuList": [],
                    "skuMap": null,
                    "skuSpecList": [],
                    "soldOut": false,
                    "status": 2,
                    "tagList": [],
                    "underShelf": false,
                    "unitPrice": 0
                },
                {
                    "attrList": [],
                    "colorNum": 0,
                    "comments": [],
                    "gradientPrice": null,
                    "hdrkDetailVOList": [],
                    "id": 1109015,
                    "issueList": [],
                    "itemDetail": null,
                    "limitedFlag": false,
                    "listPicUrl": "",
                    "name": "日本制造 美浓烧樱花餐具",
                    "newItemFlag": false,
                    "pieceNum": 0,
                    "pieceUnitDesc": "件",
                    "primaryPicUrl": "http://yanxuan.nosdn.127.net/df64b6f3a624fe9974c16c5a6a5eaec1.png",
                    "primarySkuId": 1110077,
                    "primarySkuPreSellPrice": 0,
                    "primarySkuPreSellStatus": 0,
                    "rank": 7,
                    "reportPicList": [],
                    "retailPrice": 25,
                    "sellVolume": 357,
                    "seoTitle": "",
                    "simpleDesc": "千年传承美浓，日式革新餐具",
                    "skuList": [],
                    "skuMap": null,
                    "skuSpecList": [],
                    "soldOut": false,
                    "status": 4,
                    "tagList": [],
                    "underShelf": false,
                    "unitPrice": 0
                },
                {
                    "attrList": [],
                    "colorNum": 0,
                    "comments": [],
                    "gradientPrice": null,
                    "hdrkDetailVOList": [],
                    "id": 1091003,
                    "issueList": [],
                    "itemDetail": null,
                    "limitedFlag": false,
                    "listPicUrl": "",
                    "name": "日本制造 创意多功能储米桶",
                    "newItemFlag": false,
                    "pieceNum": 0,
                    "pieceUnitDesc": "件",
                    "primaryPicUrl": "http://yanxuan.nosdn.127.net/9c9aa1e7b07fe84eee993ce84fed08a2.png",
                    "primarySkuId": 1096006,
                    "primarySkuPreSellPrice": 0,
                    "primarySkuPreSellStatus": 0,
                    "rank": 97,
                    "reportPicList": [],
                    "retailPrice": 99,
                    "sellVolume": 633,
                    "seoTitle": "",
                    "simpleDesc": "日本食品级安全材质，多功能储米设计",
                    "skuList": [],
                    "skuMap": null,
                    "skuSpecList": [],
                    "soldOut": false,
                    "status": 2,
                    "tagList": [],
                    "underShelf": false,
                    "unitPrice": 0
                },
                {
                    "attrList": [],
                    "colorNum": 0,
                    "comments": [],
                    "gradientPrice": null,
                    "hdrkDetailVOList": [],
                    "id": 1091005,
                    "issueList": [],
                    "itemDetail": null,
                    "limitedFlag": false,
                    "listPicUrl": "",
                    "name": "日本制造 创意多功能洗衣盆",
                    "newItemFlag": false,
                    "pieceNum": 0,
                    "pieceUnitDesc": "件",
                    "primaryPicUrl": "http://yanxuan.nosdn.127.net/ca372cc5ebec17fe576232907b47a27a.png",
                    "primarySkuId": 1096010,
                    "primarySkuPreSellPrice": 0,
                    "primarySkuPreSellStatus": 0,
                    "rank": 98,
                    "reportPicList": [],
                    "retailPrice": 49,
                    "sellVolume": 878,
                    "seoTitle": "",
                    "simpleDesc": "日本创意设计，一体式搓衣盆",
                    "skuList": [],
                    "skuMap": null,
                    "skuSpecList": [],
                    "soldOut": false,
                    "status": 2,
                    "tagList": [],
                    "underShelf": false,
                    "unitPrice": 0
                },
                {
                    "attrList": [],
                    "colorNum": 0,
                    "comments": [],
                    "gradientPrice": null,
                    "hdrkDetailVOList": [],
                    "id": 1109016,
                    "issueList": [],
                    "itemDetail": null,
                    "limitedFlag": false,
                    "listPicUrl": "",
                    "name": "日本制造 美浓烧古染餐具",
                    "newItemFlag": false,
                    "pieceNum": 0,
                    "pieceUnitDesc": "件",
                    "primaryPicUrl": "http://yanxuan.nosdn.127.net/044e15de01ef4bf8f96822257811f5ad.png",
                    "primarySkuId": 1110081,
                    "primarySkuPreSellPrice": 0,
                    "primarySkuPreSellStatus": 0,
                    "rank": 6,
                    "reportPicList": [],
                    "retailPrice": 35,
                    "sellVolume": 0,
                    "seoTitle": "",
                    "simpleDesc": "千年传承美浓，日式革新餐具",
                    "skuList": [],
                    "skuMap": null,
                    "skuSpecList": [],
                    "soldOut": false,
                    "status": 4,
                    "tagList": [],
                    "underShelf": false,
                    "unitPrice": 0
                },
                {
                    "attrList": [],
                    "colorNum": 0,
                    "comments": [],
                    "gradientPrice": null,
                    "hdrkDetailVOList": [],
                    "id": 1091004,
                    "issueList": [],
                    "itemDetail": null,
                    "limitedFlag": false,
                    "listPicUrl": "",
                    "name": "日本制造 内衣收纳五件套",
                    "newItemFlag": false,
                    "pieceNum": 0,
                    "pieceUnitDesc": "件",
                    "primaryPicUrl": "http://yanxuan.nosdn.127.net/fefdc9b2cce2acd1d62e63d605a45d6e.png",
                    "primarySkuId": 1096007,
                    "primarySkuPreSellPrice": 0,
                    "primarySkuPreSellStatus": 0,
                    "rank": 99,
                    "reportPicList": [],
                    "retailPrice": 139,
                    "sellVolume": 0,
                    "seoTitle": "",
                    "simpleDesc": "经典实用多组合收纳，日本优良材质",
                    "skuList": [],
                    "skuMap": null,
                    "skuSpecList": [],
                    "soldOut": false,
                    "status": 2,
                    "tagList": [],
                    "underShelf": false,
                    "unitPrice": 0
                }
            ]
        },
        {
            "category": {
                "bannerUrl": "http://yanxuan.nosdn.127.net/e7b37b1ed5c18d63dc3e6c3f1aa85d8a.png",
                "frontDesc": "遇见节日的美好",
                "frontName": "限量礼盒限时发售",
                "iconUrl": "",
                "id": 1021000,
                "imgUrl": "",
                "level": "L2",
                "name": "节日礼盒",
                "showIndex": 2,
                "subCateList": [],
                "superCategoryId": 0
            },
            "itemList": [
                {
                    "attrList": [],
                    "colorNum": 0,
                    "comments": [],
                    "gradientPrice": null,
                    "hdrkDetailVOList": [],
                    "id": 1109035,
                    "issueList": [],
                    "itemDetail": null,
                    "limitedFlag": false,
                    "listPicUrl": "",
                    "name": "圣诞限量版臻享礼盒",
                    "newItemFlag": true,
                    "pieceNum": 0,
                    "pieceUnitDesc": "件",
                    "primaryPicUrl": "http://yanxuan.nosdn.127.net/4be8be461c3522db204f8bfd031a6dc8.png",
                    "primarySkuId": 1110158,
                    "primarySkuPreSellPrice": 699,
                    "primarySkuPreSellStatus": 1,
                    "rank": 99,
                    "reportPicList": [],
                    "retailPrice": 699,
                    "sellVolume": 354,
                    "seoTitle": "",
                    "simpleDesc": "【预售】预计12月21日发货",
                    "skuList": [],
                    "skuMap": null,
                    "skuSpecList": [],
                    "soldOut": false,
                    "status": 2,
                    "tagList": [],
                    "underShelf": false,
                    "unitPrice": 0
                },
                {
                    "attrList": [],
                    "colorNum": 0,
                    "comments": [],
                    "gradientPrice": null,
                    "hdrkDetailVOList": [],
                    "id": 1109036,
                    "issueList": [],
                    "itemDetail": null,
                    "limitedFlag": false,
                    "listPicUrl": "",
                    "name": "圣诞限量版绅士礼盒",
                    "newItemFlag": true,
                    "pieceNum": 0,
                    "pieceUnitDesc": "件",
                    "primaryPicUrl": "http://yanxuan.nosdn.127.net/df3ba511fb47e850fcf86304ad961ef8.png",
                    "primarySkuId": 1110159,
                    "primarySkuPreSellPrice": 319,
                    "primarySkuPreSellStatus": 1,
                    "rank": 99,
                    "reportPicList": [],
                    "retailPrice": 319,
                    "sellVolume": 508,
                    "seoTitle": "",
                    "simpleDesc": "【预售】预计12月21日发货",
                    "skuList": [],
                    "skuMap": null,
                    "skuSpecList": [],
                    "soldOut": false,
                    "status": 2,
                    "tagList": [],
                    "underShelf": false,
                    "unitPrice": 0
                },
                {
                    "attrList": [],
                    "colorNum": 0,
                    "comments": [],
                    "gradientPrice": null,
                    "hdrkDetailVOList": [],
                    "id": 1109038,
                    "issueList": [],
                    "itemDetail": null,
                    "limitedFlag": false,
                    "listPicUrl": "",
                    "name": "圣诞限量版Lady礼盒",
                    "newItemFlag": true,
                    "pieceNum": 0,
                    "pieceUnitDesc": "件",
                    "primaryPicUrl": "http://yanxuan.nosdn.127.net/8ff4319b76b6a59fbb185fb15e8298ca.png",
                    "primarySkuId": 1110162,
                    "primarySkuPreSellPrice": 159,
                    "primarySkuPreSellStatus": 1,
                    "rank": 99,
                    "reportPicList": [],
                    "retailPrice": 159,
                    "sellVolume": 0,
                    "seoTitle": "",
                    "simpleDesc": "【预售】预计12月21日发货",
                    "skuList": [],
                    "skuMap": null,
                    "skuSpecList": [],
                    "soldOut": false,
                    "status": 2,
                    "tagList": [],
                    "underShelf": false,
                    "unitPrice": 0
                }
            ]
        },
        {
            "category": {
                "bannerUrl": "http://yanxuan.nosdn.127.net/a0352c57c60ce4f68370ecdab6a30857.png",
                "frontDesc": "出口品质，严选贴合萌宠生活习惯用品。",
                "frontName": "抑菌除味，打造宠物舒适空间",
                "iconUrl": "",
                "id": 1017000,
                "imgUrl": "",
                "level": "L2",
                "name": "宠物",
                "showIndex": 3,
                "subCateList": [],
                "superCategoryId": 0
            },
            "itemList": [
                {
                    "attrList": [],
                    "colorNum": 0,
                    "comments": [],
                    "gradientPrice": null,
                    "hdrkDetailVOList": [],
                    "id": 1064004,
                    "issueList": [],
                    "itemDetail": null,
                    "limitedFlag": false,
                    "listPicUrl": "",
                    "name": "方形封闭式宠物窝",
                    "newItemFlag": false,
                    "pieceNum": 0,
                    "pieceUnitDesc": "件",
                    "primaryPicUrl": "http://yanxuan.nosdn.127.net/337da7094c1df295ca0f0b8baa55b2d5.png",
                    "primarySkuId": 1066005,
                    "primarySkuPreSellPrice": 0,
                    "primarySkuPreSellStatus": 0,
                    "rank": 1,
                    "reportPicList": [],
                    "retailPrice": 99,
                    "sellVolume": 719,
                    "seoTitle": "",
                    "simpleDesc": "封闭式设计猫咪独享",
                    "skuList": [],
                    "skuMap": null,
                    "skuSpecList": [],
                    "soldOut": false,
                    "status": 2,
                    "tagList": [],
                    "underShelf": false,
                    "unitPrice": 0
                },
                {
                    "attrList": [],
                    "colorNum": 0,
                    "comments": [],
                    "gradientPrice": null,
                    "hdrkDetailVOList": [],
                    "id": 1064002,
                    "issueList": [],
                    "itemDetail": null,
                    "limitedFlag": false,
                    "listPicUrl": "",
                    "name": "秋冬加厚条纹宠物窝",
                    "newItemFlag": false,
                    "pieceNum": 0,
                    "pieceUnitDesc": "件",
                    "primaryPicUrl": "http://yanxuan.nosdn.127.net/48dbfe207b2203ef45055dcc9cedbe60.png",
                    "primarySkuId": 1066002,
                    "primarySkuPreSellPrice": 0,
                    "primarySkuPreSellStatus": 0,
                    "rank": 2,
                    "reportPicList": [],
                    "retailPrice": 69,
                    "sellVolume": 1981,
                    "seoTitle": "",
                    "simpleDesc": "时尚牛仔，加厚温暖",
                    "skuList": [],
                    "skuMap": null,
                    "skuSpecList": [],
                    "soldOut": false,
                    "status": 2,
                    "tagList": [],
                    "underShelf": false,
                    "unitPrice": 0
                },
                {
                    "attrList": [],
                    "colorNum": 0,
                    "comments": [],
                    "gradientPrice": null,
                    "hdrkDetailVOList": [],
                    "id": 1064003,
                    "issueList": [],
                    "itemDetail": null,
                    "limitedFlag": false,
                    "listPicUrl": "",
                    "name": "六边形南瓜式宠物窝",
                    "newItemFlag": false,
                    "pieceNum": 0,
                    "pieceUnitDesc": "件",
                    "primaryPicUrl": "http://yanxuan.nosdn.127.net/58ed94b63b39339e7814f1339013793c.png",
                    "primarySkuId": 1066004,
                    "primarySkuPreSellPrice": 0,
                    "primarySkuPreSellStatus": 0,
                    "rank": 3,
                    "reportPicList": [],
                    "retailPrice": 89,
                    "sellVolume": 1232,
                    "seoTitle": "",
                    "simpleDesc": "给萌宠柔软包裹的归家感",
                    "skuList": [],
                    "skuMap": null,
                    "skuSpecList": [],
                    "soldOut": false,
                    "status": 2,
                    "tagList": [],
                    "underShelf": false,
                    "unitPrice": 0
                },
                {
                    "attrList": [],
                    "colorNum": 0,
                    "comments": [],
                    "gradientPrice": null,
                    "hdrkDetailVOList": [],
                    "id": 1064000,
                    "issueList": [],
                    "itemDetail": null,
                    "limitedFlag": false,
                    "listPicUrl": "",
                    "name": "清新条纹开放式宠物窝",
                    "newItemFlag": false,
                    "pieceNum": 0,
                    "pieceUnitDesc": "件",
                    "primaryPicUrl": "http://yanxuan.nosdn.127.net/ebe118f94ddafe82c4a8cd51da6ff183.png",
                    "primarySkuId": 1066000,
                    "primarySkuPreSellPrice": 0,
                    "primarySkuPreSellStatus": 0,
                    "rank": 4,
                    "reportPicList": [],
                    "retailPrice": 79,
                    "sellVolume": 1671,
                    "seoTitle": "",
                    "simpleDesc": "清凉触感，耐抓耐磨",
                    "skuList": [],
                    "skuMap": null,
                    "skuSpecList": [],
                    "soldOut": false,
                    "status": 2,
                    "tagList": [],
                    "underShelf": false,
                    "unitPrice": 0
                },
                {
                    "attrList": [],
                    "colorNum": 2,
                    "comments": [],
                    "gradientPrice": null,
                    "hdrkDetailVOList": [],
                    "id": 1071005,
                    "issueList": [],
                    "itemDetail": null,
                    "limitedFlag": false,
                    "listPicUrl": "",
                    "name": "便携多功能宠物拾便器",
                    "newItemFlag": false,
                    "pieceNum": 0,
                    "pieceUnitDesc": "件",
                    "primaryPicUrl": "http://yanxuan.nosdn.127.net/07a47d73e2eb53b1a7939219a4e63618.png",
                    "primarySkuId": 1075044,
                    "primarySkuPreSellPrice": 0,
                    "primarySkuPreSellStatus": 0,
                    "rank": 11,
                    "reportPicList": [],
                    "retailPrice": 39,
                    "sellVolume": 514,
                    "seoTitle": "",
                    "simpleDesc": "方便携带，环保卫生",
                    "skuList": [],
                    "skuMap": null,
                    "skuSpecList": [],
                    "soldOut": false,
                    "status": 2,
                    "tagList": [],
                    "underShelf": false,
                    "unitPrice": 0
                },
                {
                    "attrList": [],
                    "colorNum": 2,
                    "comments": [],
                    "gradientPrice": null,
                    "hdrkDetailVOList": [],
                    "id": 1071004,
                    "issueList": [],
                    "itemDetail": null,
                    "limitedFlag": false,
                    "listPicUrl": "",
                    "name": "日式圆形宠物盆猫砂盆",
                    "newItemFlag": false,
                    "pieceNum": 0,
                    "pieceUnitDesc": "件",
                    "primaryPicUrl": "http://yanxuan.nosdn.127.net/f0abf2bf11c8d303212e4a0c1106bb73.png",
                    "primarySkuId": 1075042,
                    "primarySkuPreSellPrice": 0,
                    "primarySkuPreSellStatus": 0,
                    "rank": 12,
                    "reportPicList": [],
                    "retailPrice": 89,
                    "sellVolume": 681,
                    "seoTitle": "",
                    "simpleDesc": "日式配色，圆滑细腻",
                    "skuList": [],
                    "skuMap": null,
                    "skuSpecList": [],
                    "soldOut": false,
                    "status": 2,
                    "tagList": [],
                    "underShelf": false,
                    "unitPrice": 0
                },
                {
                    "attrList": [],
                    "colorNum": 0,
                    "comments": [],
                    "gradientPrice": null,
                    "hdrkDetailVOList": [],
                    "id": 1071006,
                    "issueList": [],
                    "itemDetail": null,
                    "limitedFlag": false,
                    "listPicUrl": "",
                    "name": "清新宠物水食钵食盆",
                    "newItemFlag": false,
                    "pieceNum": 0,
                    "pieceUnitDesc": "件",
                    "primaryPicUrl": "http://yanxuan.nosdn.127.net/d206e0d15955b4d76431a752f2c94f9f.png",
                    "primarySkuId": 1075047,
                    "primarySkuPreSellPrice": 0,
                    "primarySkuPreSellStatus": 0,
                    "rank": 13,
                    "reportPicList": [],
                    "retailPrice": 9.9,
                    "sellVolume": 534,
                    "seoTitle": "",
                    "simpleDesc": "含银离子的洁净除菌食盆",
                    "skuList": [],
                    "skuMap": null,
                    "skuSpecList": [],
                    "soldOut": false,
                    "status": 2,
                    "tagList": [],
                    "underShelf": false,
                    "unitPrice": 0
                },
                {
                    "attrList": [],
                    "colorNum": 0,
                    "comments": [],
                    "gradientPrice": null,
                    "hdrkDetailVOList": [],
                    "id": 1092038,
                    "issueList": [],
                    "itemDetail": null,
                    "limitedFlag": false,
                    "listPicUrl": "",
                    "name": "日式天然桐木材质猫抓板",
                    "newItemFlag": false,
                    "pieceNum": 0,
                    "pieceUnitDesc": "件",
                    "primaryPicUrl": "http://yanxuan.nosdn.127.net/1aba9ed9c9160b9ca8e7de58ce4e46b1.png",
                    "primarySkuId": 1097179,
                    "primarySkuPreSellPrice": 0,
                    "primarySkuPreSellStatus": 0,
                    "rank": 21,
                    "reportPicList": [],
                    "retailPrice": 39,
                    "sellVolume": 359,
                    "seoTitle": "",
                    "simpleDesc": "天然桐木，耐磨耐抓",
                    "skuList": [],
                    "skuMap": null,
                    "skuSpecList": [],
                    "soldOut": false,
                    "status": 2,
                    "tagList": [],
                    "underShelf": false,
                    "unitPrice": 0
                },
                {
                    "attrList": [],
                    "colorNum": 0,
                    "comments": [],
                    "gradientPrice": null,
                    "hdrkDetailVOList": [],
                    "id": 1092039,
                    "issueList": [],
                    "itemDetail": null,
                    "limitedFlag": false,
                    "listPicUrl": "",
                    "name": "圆钵碗状高密材质猫抓板",
                    "newItemFlag": false,
                    "pieceNum": 0,
                    "pieceUnitDesc": "件",
                    "primaryPicUrl": "http://yanxuan.nosdn.127.net/d8c18953bcb05f0b07d6b48e2d159ace.png",
                    "primarySkuId": 1097180,
                    "primarySkuPreSellPrice": 0,
                    "primarySkuPreSellStatus": 0,
                    "rank": 22,
                    "reportPicList": [],
                    "retailPrice": 59,
                    "sellVolume": 194,
                    "seoTitle": "",
                    "simpleDesc": "可抓可睡，一物两用",
                    "skuList": [],
                    "skuMap": null,
                    "skuSpecList": [],
                    "soldOut": false,
                    "status": 2,
                    "tagList": [],
                    "underShelf": false,
                    "unitPrice": 0
                },
                {
                    "attrList": [],
                    "colorNum": 3,
                    "comments": [],
                    "gradientPrice": null,
                    "hdrkDetailVOList": [],
                    "id": 1086024,
                    "issueList": [],
                    "itemDetail": null,
                    "limitedFlag": false,
                    "listPicUrl": "",
                    "name": "荧光平条宠物牵引绳",
                    "newItemFlag": false,
                    "pieceNum": 0,
                    "pieceUnitDesc": "件",
                    "primaryPicUrl": "http://yanxuan.nosdn.127.net/af899cfaa13f515ecb9cf9a33f41370a.png",
                    "primarySkuId": 1091111,
                    "primarySkuPreSellPrice": 0,
                    "primarySkuPreSellStatus": 0,
                    "rank": 31,
                    "reportPicList": [],
                    "retailPrice": 9.9,
                    "sellVolume": 2507,
                    "seoTitle": "",
                    "simpleDesc": "编织荧光，夜间防走失",
                    "skuList": [],
                    "skuMap": null,
                    "skuSpecList": [],
                    "soldOut": false,
                    "status": 2,
                    "tagList": [],
                    "underShelf": false,
                    "unitPrice": 0
                },
                {
                    "attrList": [],
                    "colorNum": 2,
                    "comments": [],
                    "gradientPrice": null,
                    "hdrkDetailVOList": [],
                    "id": 1086023,
                    "issueList": [],
                    "itemDetail": null,
                    "limitedFlag": false,
                    "listPicUrl": "",
                    "name": "彩色波点缓冲宠物牵引绳",
                    "newItemFlag": false,
                    "pieceNum": 0,
                    "pieceUnitDesc": "件",
                    "primaryPicUrl": "http://yanxuan.nosdn.127.net/121a99e896b3e332c102eb5f6f9b3406.png",
                    "primarySkuId": 1091109,
                    "primarySkuPreSellPrice": 0,
                    "primarySkuPreSellStatus": 0,
                    "rank": 32,
                    "reportPicList": [],
                    "retailPrice": 19.9,
                    "sellVolume": 1101,
                    "seoTitle": "",
                    "simpleDesc": "精致合金，萌趣波点",
                    "skuList": [],
                    "skuMap": null,
                    "skuSpecList": [],
                    "soldOut": false,
                    "status": 2,
                    "tagList": [],
                    "underShelf": false,
                    "unitPrice": 0
                },
                {
                    "attrList": [],
                    "colorNum": 0,
                    "comments": [],
                    "gradientPrice": null,
                    "hdrkDetailVOList": [],
                    "id": 1086026,
                    "issueList": [],
                    "itemDetail": null,
                    "limitedFlag": false,
                    "listPicUrl": "",
                    "name": "复古实心交织宠物牵引绳",
                    "newItemFlag": false,
                    "pieceNum": 0,
                    "pieceUnitDesc": "件",
                    "primaryPicUrl": "http://yanxuan.nosdn.127.net/caecdaa37d9cbcff980cee0968911e34.png",
                    "primarySkuId": 1091115,
                    "primarySkuPreSellPrice": 0,
                    "primarySkuPreSellStatus": 0,
                    "rank": 33,
                    "reportPicList": [],
                    "retailPrice": 29,
                    "sellVolume": 420,
                    "seoTitle": "",
                    "simpleDesc": "实心黑色编织仿皮质宠物牵引绳",
                    "skuList": [],
                    "skuMap": null,
                    "skuSpecList": [],
                    "soldOut": false,
                    "status": 2,
                    "tagList": [],
                    "underShelf": false,
                    "unitPrice": 0
                },
                {
                    "attrList": [],
                    "colorNum": 0,
                    "comments": [],
                    "gradientPrice": null,
                    "hdrkDetailVOList": [],
                    "id": 1086025,
                    "issueList": [],
                    "itemDetail": null,
                    "limitedFlag": false,
                    "listPicUrl": "",
                    "name": "美式精编麻花圆绳宠物牵引绳",
                    "newItemFlag": false,
                    "pieceNum": 0,
                    "pieceUnitDesc": "件",
                    "primaryPicUrl": "http://yanxuan.nosdn.127.net/78eff56b293c8354bc9ac496fc2c5179.png",
                    "primarySkuId": 1091114,
                    "primarySkuPreSellPrice": 0,
                    "primarySkuPreSellStatus": 0,
                    "rank": 34,
                    "reportPicList": [],
                    "retailPrice": 49,
                    "sellVolume": 447,
                    "seoTitle": "",
                    "simpleDesc": "编织纹理，牢固精致",
                    "skuList": [],
                    "skuMap": null,
                    "skuSpecList": [],
                    "soldOut": false,
                    "status": 2,
                    "tagList": [],
                    "underShelf": false,
                    "unitPrice": 0
                }
            ]
        },
        {
            "category": {
                "bannerUrl": "http://yanxuan.nosdn.127.net/83d22ca3d1c8f94ee23ca96de489864c.png",
                "frontDesc": "踏青出游，便携不误好心情",
                "frontName": "MUJI、Nike等制造商出品",
                "iconUrl": "",
                "id": 1008005,
                "imgUrl": "",
                "level": "L2",
                "name": "户外",
                "showIndex": 4,
                "subCateList": [],
                "superCategoryId": 0
            },
            "itemList": [
                {
                    "attrList": [],
                    "colorNum": 2,
                    "comments": [],
                    "gradientPrice": null,
                    "hdrkDetailVOList": [],
                    "id": 1062021,
                    "issueList": [],
                    "itemDetail": null,
                    "limitedFlag": false,
                    "listPicUrl": "",
                    "name": "加厚绒面多用防水户外垫",
                    "newItemFlag": false,
                    "pieceNum": 0,
                    "pieceUnitDesc": "件",
                    "primaryPicUrl": "http://yanxuan.nosdn.127.net/0780250ca7171b9ec9efa388742ccf84.png",
                    "primarySkuId": 1063028,
                    "primarySkuPreSellPrice": 0,
                    "primarySkuPreSellStatus": 0,
                    "rank": 11,
                    "reportPicList": [],
                    "retailPrice": 89,
                    "sellVolume": 405,
                    "seoTitle": "",
                    "simpleDesc": "耐磨耐脏，细腻温暖",
                    "skuList": [],
                    "skuMap": null,
                    "skuSpecList": [],
                    "soldOut": false,
                    "status": 2,
                    "tagList": [],
                    "underShelf": false,
                    "unitPrice": 0
                },
                {
                    "attrList": [],
                    "colorNum": 2,
                    "comments": [],
                    "gradientPrice": null,
                    "hdrkDetailVOList": [],
                    "id": 1023013,
                    "issueList": [],
                    "itemDetail": null,
                    "limitedFlag": false,
                    "listPicUrl": "",
                    "name": "便携式多功能防水户外垫",
                    "newItemFlag": false,
                    "pieceNum": 0,
                    "pieceUnitDesc": "件",
                    "primaryPicUrl": "http://yanxuan.nosdn.127.net/7cd8f7a3e68357b7c7093ecbf6cdbac4.png",
                    "primarySkuId": 1022031,
                    "primarySkuPreSellPrice": 0,
                    "primarySkuPreSellStatus": 0,
                    "rank": 12,
                    "reportPicList": [],
                    "retailPrice": 79,
                    "sellVolume": 194,
                    "seoTitle": "",
                    "simpleDesc": "防水便携，出游必备",
                    "skuList": [],
                    "skuMap": null,
                    "skuSpecList": [],
                    "soldOut": false,
                    "status": 2,
                    "tagList": [],
                    "underShelf": false,
                    "unitPrice": 0
                }
            ]
        },
        {
            "category": {
                "bannerUrl": "http://yanxuan.nosdn.127.net/b5e9f174404ef81b8603d6ecc304c62e.png",
                "frontDesc": "湖南卫视《夏日甜心》授权，独家发售大猫熊同款周边",
                "frontName": "湖南卫视《夏日甜心》授权，独家发售",
                "iconUrl": "",
                "id": 1018000,
                "imgUrl": "",
                "level": "L2",
                "name": "夏日甜心",
                "showIndex": 5,
                "subCateList": [],
                "superCategoryId": 0
            },
            "itemList": [
                {
                    "attrList": [],
                    "colorNum": 0,
                    "comments": [],
                    "gradientPrice": null,
                    "hdrkDetailVOList": [],
                    "id": 1006032,
                    "issueList": [],
                    "itemDetail": null,
                    "limitedFlag": false,
                    "listPicUrl": "",
                    "name": "夏日甜心公仔抱枕",
                    "newItemFlag": false,
                    "pieceNum": 0,
                    "pieceUnitDesc": "件",
                    "primaryPicUrl": "http://yanxuan.nosdn.127.net/329945d25afdf6cd372a1aadcbb4aadd.png",
                    "primarySkuId": 1006081,
                    "primarySkuPreSellPrice": 0,
                    "primarySkuPreSellStatus": 0,
                    "rank": 99,
                    "reportPicList": [],
                    "retailPrice": 78,
                    "sellVolume": 433,
                    "seoTitle": "",
                    "simpleDesc": "精准走线，自由靠卧",
                    "skuList": [],
                    "skuMap": null,
                    "skuSpecList": [],
                    "soldOut": false,
                    "status": 2,
                    "tagList": [],
                    "underShelf": false,
                    "unitPrice": 0
                },
                {
                    "attrList": [],
                    "colorNum": 0,
                    "comments": [],
                    "gradientPrice": null,
                    "hdrkDetailVOList": [],
                    "id": 1011003,
                    "issueList": [],
                    "itemDetail": null,
                    "limitedFlag": false,
                    "listPicUrl": "",
                    "name": "夏日甜心方抱枕",
                    "newItemFlag": false,
                    "pieceNum": 0,
                    "pieceUnitDesc": "件",
                    "primaryPicUrl": "http://yanxuan.nosdn.127.net/de241c3fb08b0d706d71df0480b3aae4.png",
                    "primarySkuId": 1010015,
                    "primarySkuPreSellPrice": 0,
                    "primarySkuPreSellStatus": 0,
                    "rank": 99,
                    "reportPicList": [],
                    "retailPrice": 99,
                    "sellVolume": 44,
                    "seoTitle": "",
                    "simpleDesc": "甜心宝贝的温度，抱枕知道",
                    "skuList": [],
                    "skuMap": null,
                    "skuSpecList": [],
                    "soldOut": false,
                    "status": 2,
                    "tagList": [],
                    "underShelf": false,
                    "unitPrice": 0
                },
                {
                    "attrList": [],
                    "colorNum": 2,
                    "comments": [],
                    "gradientPrice": null,
                    "hdrkDetailVOList": [],
                    "id": 1021002,
                    "issueList": [],
                    "itemDetail": null,
                    "limitedFlag": false,
                    "listPicUrl": "",
                    "name": "夏日甜心四件套",
                    "newItemFlag": false,
                    "pieceNum": 0,
                    "pieceUnitDesc": "件",
                    "primaryPicUrl": "http://yanxuan.nosdn.127.net/1171e0555f81c7e9bf9030f58babc670.png",
                    "primarySkuId": 1019006,
                    "primarySkuPreSellPrice": 0,
                    "primarySkuPreSellStatus": 0,
                    "rank": 99,
                    "reportPicList": [],
                    "retailPrice": 399,
                    "sellVolume": 43,
                    "seoTitle": "",
                    "simpleDesc": "甜心宝贝最爱，来至针织棉的呵护",
                    "skuList": [],
                    "skuMap": null,
                    "skuSpecList": [],
                    "soldOut": false,
                    "status": 2,
                    "tagList": [],
                    "underShelf": false,
                    "unitPrice": 0
                },
                {
                    "attrList": [],
                    "colorNum": 0,
                    "comments": [],
                    "gradientPrice": null,
                    "hdrkDetailVOList": [],
                    "id": 1035003,
                    "issueList": [],
                    "itemDetail": null,
                    "limitedFlag": false,
                    "listPicUrl": "",
                    "name": "夏日甜心按摩棒",
                    "newItemFlag": false,
                    "pieceNum": 0,
                    "pieceUnitDesc": "件",
                    "primaryPicUrl": "http://yanxuan.nosdn.127.net/f5b69c9d42b7f873af79ec6b33f51b46.png",
                    "primarySkuId": 1034003,
                    "primarySkuPreSellPrice": 0,
                    "primarySkuPreSellStatus": 0,
                    "rank": 99,
                    "reportPicList": [],
                    "retailPrice": 68,
                    "sellVolume": 108,
                    "seoTitle": "",
                    "simpleDesc": "随时缓解腰酸背痛",
                    "skuList": [],
                    "skuMap": null,
                    "skuSpecList": [],
                    "soldOut": false,
                    "status": 2,
                    "tagList": [],
                    "underShelf": false,
                    "unitPrice": 0
                },
                {
                    "attrList": [],
                    "colorNum": 0,
                    "comments": [],
                    "gradientPrice": null,
                    "hdrkDetailVOList": [],
                    "id": 1056012,
                    "issueList": [],
                    "itemDetail": null,
                    "limitedFlag": false,
                    "listPicUrl": "",
                    "name": "夏日甜心荷叶玫瑰茶",
                    "newItemFlag": false,
                    "pieceNum": 0,
                    "pieceUnitDesc": "件",
                    "primaryPicUrl": "http://yanxuan.nosdn.127.net/6e108ded08448f4483a2969aea192add.png",
                    "primarySkuId": 1057076,
                    "primarySkuPreSellPrice": 0,
                    "primarySkuPreSellStatus": 0,
                    "rank": 99,
                    "reportPicList": [],
                    "retailPrice": 52,
                    "sellVolume": 310,
                    "seoTitle": "",
                    "simpleDesc": "荷叶与玫瑰，碰撞的自然芬芳",
                    "skuList": [],
                    "skuMap": null,
                    "skuSpecList": [],
                    "soldOut": false,
                    "status": 2,
                    "tagList": [],
                    "underShelf": false,
                    "unitPrice": 0
                },
                {
                    "attrList": [],
                    "colorNum": 0,
                    "comments": [],
                    "gradientPrice": null,
                    "hdrkDetailVOList": [],
                    "id": 1059009,
                    "issueList": [],
                    "itemDetail": null,
                    "limitedFlag": false,
                    "listPicUrl": "",
                    "name": "夏日甜心U形枕",
                    "newItemFlag": false,
                    "pieceNum": 0,
                    "pieceUnitDesc": "件",
                    "primaryPicUrl": "http://yanxuan.nosdn.127.net/2b46a02508da79dd41434ee416208940.png",
                    "primarySkuId": 1059028,
                    "primarySkuPreSellPrice": 0,
                    "primarySkuPreSellStatus": 0,
                    "rank": 99,
                    "reportPicList": [],
                    "retailPrice": 58,
                    "sellVolume": 319,
                    "seoTitle": "",
                    "simpleDesc": "慢慢旅途，有熊出没",
                    "skuList": [],
                    "skuMap": null,
                    "skuSpecList": [],
                    "soldOut": false,
                    "status": 2,
                    "tagList": [],
                    "underShelf": false,
                    "unitPrice": 0
                },
                {
                    "attrList": [],
                    "colorNum": 0,
                    "comments": [],
                    "gradientPrice": null,
                    "hdrkDetailVOList": [],
                    "id": 1059033,
                    "issueList": [],
                    "itemDetail": null,
                    "limitedFlag": false,
                    "listPicUrl": "",
                    "name": "夏日甜心浮雕手机壳",
                    "newItemFlag": false,
                    "pieceNum": 0,
                    "pieceUnitDesc": "件",
                    "primaryPicUrl": "http://yanxuan.nosdn.127.net/81c8e1378ab295232afff10cb93acd42.png",
                    "primarySkuId": 1059093,
                    "primarySkuPreSellPrice": 0,
                    "primarySkuPreSellStatus": 0,
                    "rank": 99,
                    "reportPicList": [],
                    "retailPrice": 39,
                    "sellVolume": 486,
                    "seoTitle": "",
                    "simpleDesc": "避免磕碰，有效防震",
                    "skuList": [],
                    "skuMap": null,
                    "skuSpecList": [],
                    "soldOut": false,
                    "status": 2,
                    "tagList": [],
                    "underShelf": false,
                    "unitPrice": 0
                },
                {
                    "attrList": [],
                    "colorNum": 0,
                    "comments": [],
                    "gradientPrice": null,
                    "hdrkDetailVOList": [],
                    "id": 1066000,
                    "issueList": [],
                    "itemDetail": null,
                    "limitedFlag": false,
                    "listPicUrl": "",
                    "name": "夏日甜心纯棉柔巾",
                    "newItemFlag": false,
                    "pieceNum": 0,
                    "pieceUnitDesc": "件",
                    "primaryPicUrl": "http://yanxuan.nosdn.127.net/e357a69fabe55ea1199db76847045117.png",
                    "primarySkuId": 1069001,
                    "primarySkuPreSellPrice": 0,
                    "primarySkuPreSellStatus": 0,
                    "rank": 99,
                    "reportPicList": [],
                    "retailPrice": 19,
                    "sellVolume": 2,
                    "seoTitle": "",
                    "simpleDesc": "天然棉花之作，舒适无敏感",
                    "skuList": [],
                    "skuMap": null,
                    "skuSpecList": [],
                    "soldOut": false,
                    "status": 2,
                    "tagList": [],
                    "underShelf": false,
                    "unitPrice": 0
                },
                {
                    "attrList": [],
                    "colorNum": 0,
                    "comments": [],
                    "gradientPrice": null,
                    "hdrkDetailVOList": [],
                    "id": 1066011,
                    "issueList": [],
                    "itemDetail": null,
                    "limitedFlag": false,
                    "listPicUrl": "",
                    "name": "夏日甜心刺绣毛巾",
                    "newItemFlag": false,
                    "pieceNum": 2,
                    "pieceUnitDesc": "条",
                    "primaryPicUrl": "http://yanxuan.nosdn.127.net/2c79e3185395553f8f29f206cf308ce0.png",
                    "primarySkuId": 1069016,
                    "primarySkuPreSellPrice": 0,
                    "primarySkuPreSellStatus": 0,
                    "rank": 99,
                    "reportPicList": [],
                    "retailPrice": 69,
                    "sellVolume": 174,
                    "seoTitle": "",
                    "simpleDesc": "蓬松柔软，吸水性强",
                    "skuList": [],
                    "skuMap": null,
                    "skuSpecList": [],
                    "soldOut": false,
                    "status": 2,
                    "tagList": [],
                    "underShelf": false,
                    "unitPrice": 0
                },
                {
                    "attrList": [],
                    "colorNum": 2,
                    "comments": [],
                    "gradientPrice": null,
                    "hdrkDetailVOList": [],
                    "id": 1066031,
                    "issueList": [],
                    "itemDetail": null,
                    "limitedFlag": false,
                    "listPicUrl": "",
                    "name": "夏日甜心笔记本",
                    "newItemFlag": false,
                    "pieceNum": 0,
                    "pieceUnitDesc": "件",
                    "primaryPicUrl": "http://yanxuan.nosdn.127.net/5f227038e510b1c950b6f7a11ceb288c.png",
                    "primarySkuId": 1069136,
                    "primarySkuPreSellPrice": 0,
                    "primarySkuPreSellStatus": 0,
                    "rank": 99,
                    "reportPicList": [],
                    "retailPrice": 29,
                    "sellVolume": 564,
                    "seoTitle": "",
                    "simpleDesc": "空白内页，随性书写",
                    "skuList": [],
                    "skuMap": null,
                    "skuSpecList": [],
                    "soldOut": false,
                    "status": 2,
                    "tagList": [],
                    "underShelf": false,
                    "unitPrice": 0
                }
            ]
        }
    ],
    "categoryList": [
        {
            "bannerUrl": "http://yanxuan.nosdn.127.net/92357337378cce650797444bc107b0f7.jpg",
            "frontDesc": "回家，放松身心",
            "frontName": "回家，放松身心",
            "iconUrl": "http://yanxuan.nosdn.127.net/a45c2c262a476fea0b9fc684fed91ef5.png",
            "id": 1005000,
            "imgUrl": "//nos.netease.com/yanxuan/f0d0e1a542e2095861b42bf789d948ce.jpg",
            "level": "L1",
            "name": "居家",
            "showIndex": 1,
            "subCateList": [],
            "superCategoryId": 0
        },
        {
            "bannerUrl": "http://yanxuan.nosdn.127.net/f4ff8b3d5b0767d4e578575c1fd6b921.jpg",
            "frontDesc": "厨房",
            "frontName": "爱，囿于厨房",
            "iconUrl": "http://yanxuan.nosdn.127.net/ad8b00d084cb7d0958998edb5fee9c0a.png",
            "id": 1005001,
            "imgUrl": "//nos.netease.com/yanxuan/88855173a0cfcfd889ee6394a3259c4f.jpg",
            "level": "L1",
            "name": "餐厨",
            "showIndex": 2,
            "subCateList": [],
            "superCategoryId": 0
        },
        {
            "bannerUrl": "http://yanxuan.nosdn.127.net/cad5aba2bc52d3b8adfd0232c9814de2.jpg",
            "frontDesc": "配角，亦是主角",
            "frontName": "配角，亦是主角",
            "iconUrl": "http://yanxuan.nosdn.127.net/11abb11c4cfdee59abfb6d16caca4c6a.png",
            "id": 1008000,
            "imgUrl": "//nos.netease.com/yanxuan/935f1ab7dcfeb4bbd4a5da9935161aaf.jpg",
            "level": "L1",
            "name": "配件",
            "showIndex": 3,
            "subCateList": [],
            "superCategoryId": 0
        },
        {
            "bannerUrl": "http://yanxuan.nosdn.127.net/003e1d1289f4f290506ac2aedbd09d35.jpg",
            "frontDesc": "贴身的，要亲肤",
            "frontName": "贴身的，要亲肤",
            "iconUrl": "http://yanxuan.nosdn.127.net/28a685c96f91584e7e4876f1397767db.png",
            "id": 1010000,
            "imgUrl": "//nos.netease.com/yanxuan/135113d6a43536b717063413fa24d69a.jpg",
            "level": "L1",
            "name": "服装",
            "showIndex": 4,
            "subCateList": [],
            "superCategoryId": 0
        },
        {
            "bannerUrl": "http://yanxuan.nosdn.127.net/ef8c49f8c92d1f86eb76dec0b5bc7cef.jpg",
            "frontDesc": "亲肤之物，严选天然",
            "frontName": "亲肤之物，严选天然",
            "iconUrl": "http://yanxuan.nosdn.127.net/9fe068776b6b1fca13053d68e9c0a83f.png",
            "id": 1013001,
            "imgUrl": "//nos.netease.com/yanxuan/14bb4a29498a0f93a1ea001f26fea1dd.jpg",
            "level": "L1",
            "name": "洗护",
            "showIndex": 5,
            "subCateList": [],
            "superCategoryId": 0
        },
        {
            "bannerUrl": "http://yanxuan.nosdn.127.net/7dc78383e44df530f543659a977740de.jpg",
            "frontDesc": "爱，从心开始",
            "frontName": "爱，从心开始",
            "iconUrl": "http://yanxuan.nosdn.127.net/1ba9967b8de1ac50fad21774a4494f5d.png",
            "id": 1011000,
            "imgUrl": "//nos.netease.com/yanxuan/8ab3c73fe90951a942e8b06d848f8743.jpg",
            "level": "L1",
            "name": "婴童",
            "showIndex": 6,
            "subCateList": [],
            "superCategoryId": 0
        },
        {
            "bannerUrl": "http://yanxuan.nosdn.127.net/d233a1a9060a22e8eb0e2b326252eece.jpg",
            "frontDesc": "解忧，每个烦恼",
            "frontName": "解忧，每个烦恼",
            "iconUrl": "http://yanxuan.nosdn.127.net/c2a3d6349e72c35931fe3b5bcd0966be.png",
            "id": 1012000,
            "imgUrl": "//nos.netease.com/yanxuan/a0c91ae573079830743dec6ee08f5841.jpg",
            "level": "L1",
            "name": "杂货",
            "showIndex": 7,
            "subCateList": [],
            "superCategoryId": 0
        },
        {
            "bannerUrl": "http://yanxuan.nosdn.127.net/dd6cc8a7e996936768db5634f12447ed.jpg",
            "frontDesc": "好吃，无添加",
            "frontName": "好吃，无添加",
            "iconUrl": "http://yanxuan.nosdn.127.net/c9280327a3fd2374c000f6bf52dff6eb.png",
            "id": 1005002,
            "imgUrl": "//nos.netease.com/yanxuan/9a29ef4f41c305a12e1459f12abd290f.jpg",
            "level": "L1",
            "name": "饮食",
            "showIndex": 8,
            "subCateList": [],
            "superCategoryId": 0
        },
        {
            "bannerUrl": "http://yanxuan.nosdn.127.net/c031900229c9f056bf65de64cc600522.jpg",
            "frontDesc": "挑选，你的生活",
            "frontName": "挑选，你的生活",
            "iconUrl": "http://yanxuan.nosdn.127.net/7093cfecb9dde1dd3eaf459623df4071.png",
            "id": 1019000,
            "imgUrl": "//nos.netease.com/yanxuan/72de912b6350b33ecf88a27498840e62.jpg",
            "level": "L1",
            "name": "其他",
            "showIndex": 9,
            "subCateList": [],
            "superCategoryId": 0
        }
    ],
    "currentCategory": {
        "bannerUrl": "http://yanxuan.nosdn.127.net/c031900229c9f056bf65de64cc600522.jpg",
        "frontDesc": "挑选，你的生活",
        "frontName": "挑选，你的生活",
        "iconUrl": "http://yanxuan.nosdn.127.net/7093cfecb9dde1dd3eaf459623df4071.png",
        "id": 1019000,
        "imgUrl": "",
        "level": "L1",
        "name": "其他",
        "showIndex": 9,
        "subCateList": [],
        "superCategoryId": 0
    }
}