{
    "message": "ad success", 
    "result": [
        {
            "ad_schedule_id": 2730, 
            "ad_schedule_name": "新人领卷", 
            "ad_schedule_num": 1, 
            "ad_source_description": "", 
            "ad_source_high": "0", 
            "ad_source_id": 3147, 
            "ad_source_imgpath": "img/home/coatmenu/coatmenu1.jpg", 
            "ad_source_margin_left": "0", 
            "ad_source_margin_top": "0", 
            "ad_source_resource": "", 
            "ad_source_title": "ÐÂÈËÁìÈ¯", 
            "ad_source_url": "http://m.wangjiu.com/activity/2016/10/10_ticket.html", 
            "ad_source_width": "0", 
            "ad_space_id": 396, 
            "p_ad_source_id": "0"
        }, 
        {
            "ad_schedule_id": 2435, 
            "ad_schedule_name": "限时秒杀", 
            "ad_schedule_num": 2, 
            "ad_source_description": "", 
            "ad_source_high": "0", 
            "ad_source_id": 3034, 
            "ad_source_imgpath": "img/home/coatmenu/coatmenu2.jpg", 
            "ad_source_margin_left": "0", 
            "ad_source_margin_top": "0", 
            "ad_source_resource": "", 
            "ad_source_title": "ÏÞÊ±ÃëÇÀ", 
            "ad_source_url": "http://m.wangjiu.com/seckill/index.html", 
            "ad_source_width": "0", 
            "ad_space_id": 396, 
            "p_ad_source_id": "0"
        }, 
        {
            "ad_schedule_id": 2305, 
            "ad_schedule_name": "拼手气", 
            "ad_schedule_num": 3, 
            "ad_source_description": "", 
            "ad_source_high": "0", 
            "ad_source_id": 2798, 
            "ad_source_imgpath": "img/home/coatmenu/coatmenu3.jpg", 
            "ad_source_margin_left": "0", 
            "ad_source_margin_top": "0", 
            "ad_source_resource": "", 
            "ad_source_title": "Æ´ÊÖÆø", 
            "ad_source_url": "http://m.wangjiu.com/activitys/yaoyiyao.html", 
            "ad_source_width": "0", 
            "ad_space_id": 396, 
            "p_ad_source_id": "0"
        }, 
        {
            "ad_schedule_id": 2306, 
            "ad_schedule_name": "乐视美酒", 
            "ad_schedule_num": 4, 
            "ad_source_description": "ÀÖÊÓÃÀ¾Æ", 
            "ad_source_high": "0", 
            "ad_source_id": 2848, 
            "ad_source_imgpath": "img/home/coatmenu/coatmenu4.jpg", 
            "ad_source_margin_left": "0", 
            "ad_source_margin_top": "0", 
            "ad_source_resource": "", 
            "ad_source_title": "ÀÖÊÓÃÀ¾Æ", 
            "ad_source_url": "http://travel.le.com/izt/homepage/index.html", 
            "ad_source_width": "0", 
            "ad_space_id": 396, 
            "p_ad_source_id": "0"
        }
    ], 
    "maxnum": "4", 
    "status": "1", 
    "info": {
        "adSpaceDescription": 396, 
        "adSpaceWidth": "90", 
        "adSpaceMaxNum": 10, 
        "adSpaceHeight": "90", 
        "status": 0, 
        "businessCode": "bÐÂÊ×Ò³ICON", 
        "adSpaceType": 1, 
        "adSpaceId": 396, 
        "adSpaceName": "bÐÂÊ×Ò³ICON"
    }
}