{
	"themeList": [{
		"recipe_type": "01",
		"locationName": null,
		"image_url": "http://pic.daydaycook.com/production/images/20161019/5df171d9-b130-4116-a8bf-917728274791",
		"recommend_type": "2",
		"description": "开抢时间：10月21日-22日",
		"click_count": 1429,
		"title": "1元抢购大闸蟹",
		"rid": 1813,
		"share_count": 5,
		"str_date": "2016-10-20 19:51:00",
		"recipe_id": 39295,
		"group_id": -2,
		"locationId": null,
		"favorite_count": 25,
		"favorite": "false",
		"makingTime": ""
	}, {
		"recipe_type": "01",
		"locationName": null,
		"image_url": "http://pic.daydaycook.com/production/images/20161019/bdf54ebd-f9e1-4d61-a2de-f37edcaa4967",
		"recommend_type": "2",
		"description": "@深夜贪食小分队",
		"click_count": 1702,
		"title": "免烤箱版烤土豆片",
		"rid": 1812,
		"share_count": 9,
		"str_date": "2016-10-20 19:50:00",
		"recipe_id": 39273,
		"group_id": -2,
		"locationId": null,
		"favorite_count": 78,
		"favorite": "false",
		"makingTime": ""
	}, {
		"recipe_type": "01",
		"locationName": null,
		"image_url": "http://pic.daydaycook.com/production/images/20161020/fd8269cd-47cb-4f4b-acb8-fefcc94b1524",
		"recommend_type": "2",
		"description": "正品海淘便当盒",
		"click_count": 282,
		"title": "带饭族的春天",
		"rid": 1809,
		"share_count": 1,
		"str_date": "2016-10-20 15:46:00",
		"recipe_id": 39313,
		"group_id": -2,
		"locationId": null,
		"favorite_count": 7,
		"favorite": "false",
		"makingTime": ""
	}, {
		"recipe_type": "01",
		"locationName": null,
		"image_url": "http://pic.daydaycook.com/production/images/20161018/6bb2d203-bc20-481a-b660-142333301bf2",
		"recommend_type": "2",
		"description": "榨菜肉丝蒸豆腐",
		"click_count": 1502,
		"title": "5款好吃的傻瓜式蒸菜",
		"rid": 1790,
		"share_count": 3,
		"str_date": "2016-10-20 09:59:00",
		"recipe_id": 39285,
		"group_id": -2,
		"locationId": null,
		"favorite_count": 24,
		"favorite": "false",
		"makingTime": null
	}, {
		"recipe_type": "01",
		"locationName": null,
		"image_url": "http://pic.daydaycook.com/production/images/20161019/02189a9a-3042-43c3-ba1c-ee6ab8aee334",
		"recommend_type": "2",
		"description": "营养师@窝小芽",
		"click_count": 1558,
		"title": "日式健康猪排（非油炸）",
		"rid": 1783,
		"share_count": 11,
		"str_date": "2016-10-19 21:53:00",
		"recipe_id": 39297,
		"group_id": -2,
		"locationId": null,
		"favorite_count": 152,
		"favorite": "false",
		"makingTime": ""
	}, {
		"recipe_type": "01",
		"locationName": null,
		"image_url": "http://pic.daydaycook.com/production/images/20161018/bfbf2253-0c35-4edd-a967-a20010a29c9a",
		"recommend_type": "2",
		"description": "蜂蜜柠檬排骨",
		"click_count": 1216,
		"title": "痛快吃肉贴秋膘",
		"rid": 1766,
		"share_count": 2,
		"str_date": "2016-10-20 00:00:00",
		"recipe_id": 39286,
		"group_id": -2,
		"locationId": null,
		"favorite_count": 33,
		"favorite": "false",
		"makingTime": null
	}, {
		"recipe_type": "01",
		"locationName": null,
		"image_url": "http://pic.daydaycook.com/production/images/20161018/dee82e7b-82ea-4198-a156-c03bff5557f6",
		"recommend_type": "2",
		"description": "暖心羊肉浓汤",
		"click_count": 3280,
		"title": "5款初秋暖心汤",
		"rid": 1764,
		"share_count": 7,
		"str_date": "2016-10-19 00:00:00",
		"recipe_id": 39283,
		"group_id": -2,
		"locationId": null,
		"favorite_count": 62,
		"favorite": "false",
		"makingTime": null
	}, {
		"recipe_type": "01",
		"locationName": null,
		"image_url": "http://pic.daydaycook.com/production/images/20161018/b29fa9ea-09a2-45a6-8eb2-9703b830f701",
		"recommend_type": "2",
		"description": "红烧肉",
		"click_count": 3418,
		"title": "百吃不腻的红烧菜",
		"rid": 1763,
		"share_count": 5,
		"str_date": "2016-10-19 00:00:00",
		"recipe_id": 39284,
		"group_id": -2,
		"locationId": null,
		"favorite_count": 59,
		"favorite": "false",
		"makingTime": null
	}, {
		"recipe_type": "01",
		"locationName": null,
		"image_url": "http://pic.daydaycook.com/production/images/20161017/f44af3f8-5ce1-4f68-ab13-74aef7c11507",
		"recommend_type": "2",
		"description": "香辣花生豇豆",
		"click_count": 4756,
		"title": "好吃不胖的创意素味",
		"rid": 1757,
		"share_count": 3,
		"str_date": "2016-10-18 00:00:00",
		"recipe_id": 39279,
		"group_id": -2,
		"locationId": null,
		"favorite_count": 76,
		"favorite": "false",
		"makingTime": ""
	}, {
		"recipe_type": "01",
		"locationName": null,
		"image_url": "http://pic.daydaycook.com/production/images/20161017/5f7e5999-7d6d-4348-9dc2-00728ecbf0c6",
		"recommend_type": "2",
		"description": "整个番茄大虾饭",
		"click_count": 4685,
		"title": "懒人最爱的一锅煮",
		"rid": 1756,
		"share_count": 7,
		"str_date": "2016-10-18 00:00:00",
		"recipe_id": 39280,
		"group_id": -2,
		"locationId": null,
		"favorite_count": 82,
		"favorite": "false",
		"makingTime": ""
	}, {
		"recipe_type": "01",
		"locationName": null,
		"image_url": "http://pic.daydaycook.com/production/images/20161017/67e6c198-b2a9-4189-8c89-85c917ea32eb",
		"recommend_type": "2",
		"description": "韭菜蛋饼",
		"click_count": 8272,
		"title": "5款快手蛋饼 搞定一周早餐",
		"rid": 1755,
		"share_count": 13,
		"str_date": "2016-10-17 14:50:00",
		"recipe_id": 39270,
		"group_id": -2,
		"locationId": null,
		"favorite_count": 131,
		"favorite": "false",
		"makingTime": ""
	}, {
		"recipe_type": "01",
		"locationName": null,
		"image_url": "http://pic.daydaycook.com/production/images/20161017/ba63d4b0-f945-4599-90ff-fa828cb53c4f",
		"recommend_type": "2",
		"description": "四川棒棒鸡",
		"click_count": 3555,
		"title": "分分钟搞定爽口小菜",
		"rid": 1754,
		"share_count": 3,
		"str_date": "2016-10-17 14:50:00",
		"recipe_id": 39271,
		"group_id": -2,
		"locationId": null,
		"favorite_count": 68,
		"favorite": "false",
		"makingTime": ""
	}, {
		"recipe_type": "01",
		"locationName": null,
		"image_url": "http://pic.daydaycook.com/production/images/20161014/933c1c9b-cf89-4ec3-a2c3-fa905a95602f",
		"recommend_type": "2",
		"description": "简单实用锅具",
		"click_count": 3397,
		"title": "好锅力荐，Norma常用锅具",
		"rid": 1751,
		"share_count": 9,
		"str_date": "2016-10-15 12:57:00",
		"recipe_id": 39255,
		"group_id": -2,
		"locationId": null,
		"favorite_count": 77,
		"favorite": "false",
		"makingTime": ""
	}, {
		"recipe_type": "01",
		"locationName": null,
		"image_url": "http://pic.daydaycook.com/production/images/20160930/7514afb4-df9b-4136-b89f-ddde3e842984",
		"recommend_type": "2",
		"description": "泰式红咖喱羊肉",
		"click_count": 20628,
		"title": "零厨艺也能成功的硬菜",
		"rid": 1750,
		"share_count": 8,
		"str_date": "2016-10-15 11:53:00",
		"recipe_id": 39128,
		"group_id": -2,
		"locationId": null,
		"favorite_count": 318,
		"favorite": "false",
		"makingTime": ""
	}, {
		"recipe_type": "01",
		"locationName": null,
		"image_url": "http://pic.daydaycook.com/production/images/20160930/35bd411d-ae45-45d7-9abb-3ea21b4b5260",
		"recommend_type": "2",
		"description": "香焖羊肋排",
		"click_count": 16288,
		"title": "一学就会的快手焖菜",
		"rid": 1749,
		"share_count": 11,
		"str_date": "2016-10-16 00:00:00",
		"recipe_id": 39126,
		"group_id": -2,
		"locationId": null,
		"favorite_count": 252,
		"favorite": "false",
		"makingTime": ""
	}, {
		"recipe_type": "01",
		"locationName": null,
		"image_url": "http://pic.daydaycook.com/production/images/20160930/5533e951-62d0-4dcd-aff0-765dc8969791",
		"recommend_type": "2",
		"description": "蜂蜜芥末去骨鸡腿",
		"click_count": 16104,
		"title": "人气下午茶top5",
		"rid": 1748,
		"share_count": 6,
		"str_date": "2016-10-16 00:00:00",
		"recipe_id": 39129,
		"group_id": -2,
		"locationId": null,
		"favorite_count": 231,
		"favorite": "false",
		"makingTime": ""
	}, {
		"recipe_type": "01",
		"locationName": null,
		"image_url": "http://pic.daydaycook.com/production/images/20160914/f766c514-c094-4d52-9cbb-c1a372d3cbb3",
		"recommend_type": "2",
		"description": "和牛炒饭",
		"click_count": 32202,
		"title": "30分钟清爽万能炒饭",
		"rid": 1746,
		"share_count": 49,
		"str_date": "2016-10-15 11:17:00",
		"recipe_id": 38978,
		"group_id": -2,
		"locationId": null,
		"favorite_count": 842,
		"favorite": "false",
		"makingTime": ""
	}, {
		"recipe_type": "01",
		"locationName": null,
		"image_url": "http://pic.daydaycook.com/production/images/20161014/29aa353a-11b2-4038-85da-d959dc3eb639",
		"recommend_type": "2",
		"description": "法国吉拉多生蚝，鲜活进口，肉肥味美！",
		"click_count": 2915,
		"title": "男人吃生蚝，他好我也好",
		"rid": 1732,
		"share_count": 14,
		"str_date": "2016-10-14 17:39:00",
		"recipe_id": 39236,
		"group_id": -2,
		"locationId": null,
		"favorite_count": 33,
		"favorite": "false",
		"makingTime": ""
	}, {
		"recipe_type": "01",
		"locationName": null,
		"image_url": "http://pic.daydaycook.com/production/images/20161014/fe80161b-5a60-479b-b8f7-83b1b4ceead2",
		"recommend_type": "2",
		"description": "台湾家常卤肉",
		"click_count": 5470,
		"title": "万能卤味小菜",
		"rid": 1729,
		"share_count": 2,
		"str_date": "2016-10-14 00:00:00",
		"recipe_id": 39199,
		"group_id": -2,
		"locationId": null,
		"favorite_count": 104,
		"favorite": "false",
		"makingTime": ""
	}, {
		"recipe_type": "01",
		"locationName": null,
		"image_url": "http://pic.daydaycook.com/production/images/20161014/f85c2916-8ba3-4d0d-873e-17d5e4ae82c3",
		"recommend_type": "2",
		"description": "电饭锅卤水鸡腿 ",
		"click_count": 17682,
		"title": "懒人必学电饭锅美食",
		"rid": 1728,
		"share_count": 19,
		"str_date": "2016-10-14 00:00:00",
		"recipe_id": 39197,
		"group_id": -2,
		"locationId": null,
		"favorite_count": 314,
		"favorite": "false",
		"makingTime": ""
	}],
	"recipeList": [{
		"recipe_type": "00",
		"locationName": null,
		"image_url": "http://pic.daydaycook.com/production/images/20160612/ce7313a8-d36f-4c67-b334-9695fbffb337",
		"recommend_type": "1",
		"description": "在台湾做月子必吃美食之一～今天用红标米酒以及一些简单的材料就能让你轻轻松松做成一道麻油鸡。",
		"click_count": 27390,
		"title": "经典台湾麻油鸡",
		"rid": 1797,
		"share_count": 153,
		"str_date": "2016-10-20 10:19:00",
		"recipe_id": 37984,
		"group_id": 0,
		"locationId": null,
		"favorite_count": 2814,
		"favorite": "false",
		"makingTime": "1小时"
	}, {
		"recipe_type": "00",
		"locationName": null,
		"image_url": "http://pic.daydaycook.com/production/ImageMigration/1000x750/recipe_34521_36491.jpg",
		"recommend_type": "1",
		"description": "今天教大家一道简单几步就能做好的韩国传统料理泡菜海鲜豆腐汤，这道汤味道酸辣开胃，是一道必备的健康营养好汤哦~！\r\n",
		"click_count": 756,
		"title": "泡菜海鲜豆腐汤",
		"rid": 1796,
		"share_count": 3,
		"str_date": "2016-10-20 10:15:00",
		"recipe_id": 34521,
		"group_id": 0,
		"locationId": null,
		"favorite_count": 76,
		"favorite": "false",
		"makingTime": "10分钟"
	}, {
		"recipe_type": "00",
		"locationName": null,
		"image_url": "http://pic.daydaycook.com/production/ImageMigration/1000x750/recipe_37501_39801.jpg",
		"recommend_type": "1",
		"description": "韩式猪肉卷",
		"click_count": 18885,
		"title": "韩式猪肉卷",
		"rid": 1793,
		"share_count": 91,
		"str_date": "2016-10-20 10:14:00",
		"recipe_id": 37501,
		"group_id": 0,
		"locationId": null,
		"favorite_count": 2927,
		"favorite": "false",
		"makingTime": "10分钟"
	}, {
		"recipe_type": "00",
		"locationName": null,
		"image_url": "http://pic.daydaycook.com/production/ImageMigration/1000x750/recipe_34581_36591.jpg",
		"recommend_type": "1",
		"description": "南瓜可以促进生长发育和保护肠胃，是一个不可错过的健康食材。今天就用它教大家做一个很受欢迎的南瓜葱油饼。\r\n",
		"click_count": 479,
		"title": "南瓜葱油饼",
		"rid": 1792,
		"share_count": 8,
		"str_date": "2016-10-20 10:13:00",
		"recipe_id": 34581,
		"group_id": 0,
		"locationId": null,
		"favorite_count": 66,
		"favorite": "false",
		"makingTime": "10分钟"
	}, {
		"recipe_type": "00",
		"locationName": null,
		"image_url": "http://pic.daydaycook.com/production/ImageMigration/1000x750/recipe_37411_39561.jpg",
		"recommend_type": "1",
		"description": "要使大闸蟹营养流失少的同时有更加美味的口感，不妨事先用啤酒腌制。啤酒独有的鲜美和酵素可以刺激蟹肉质地更加软糯。再经过翻炒和焖煮，让这道啤酒焖蟹色香味俱全，是秋日一道必不可少的家宴大餐！\r\n",
		"click_count": 13828,
		"title": "啤酒焖蟹",
		"rid": 1695,
		"share_count": 154,
		"str_date": "2016-10-11 10:40:00",
		"recipe_id": 37411,
		"group_id": 0,
		"locationId": null,
		"favorite_count": 1638,
		"favorite": "false",
		"makingTime": "1小时"
	}, {
		"recipe_type": "00",
		"locationName": null,
		"image_url": "http://pic.daydaycook.com/production/images/20160322/fb986e73-bc97-452d-8799-e26855a777f3",
		"recommend_type": "1",
		"description": "云朵蛋(Egg in a cloud)是一道见到就叫人心动的早餐小吃，利用蛋白的特性把它打至松发，就像白云的模样，将它烘成金黄色后，入口就像棉花般轻柔，感觉非常梦幻。",
		"click_count": 41038,
		"title": "培根芝士云朵蛋",
		"rid": 1694,
		"share_count": 219,
		"str_date": "2016-10-11 10:40:00",
		"recipe_id": 37817,
		"group_id": 0,
		"locationId": null,
		"favorite_count": 4090,
		"favorite": "false",
		"makingTime": "30分钟"
	}, {
		"recipe_type": "00",
		"locationName": null,
		"image_url": "http://pic.daydaycook.com/production/images/20160701/8a50360c-512c-4e27-8792-b87129a46e8b",
		"recommend_type": "1",
		"description": "浓郁的黑椒汁，再加上香甜的洋葱，将猪手炖透，味道一流，酱汁更可以用来拌饭!",
		"click_count": 28269,
		"title": "黑椒洋葱炖猪手",
		"rid": 1693,
		"share_count": 182,
		"str_date": "2016-10-11 10:40:00",
		"recipe_id": 38119,
		"group_id": 0,
		"locationId": null,
		"favorite_count": 2807,
		"favorite": "false",
		"makingTime": "1.5小时"
	}, {
		"recipe_type": "00",
		"locationName": null,
		"image_url": "http://pic.daydaycook.com/production/images/20160410/be802747-a44d-45b8-bf47-c1d6471da9cc",
		"recommend_type": "1",
		"description": "每次做黑椒炒大虾，厨房都传来阵阵香气令人食指大动，这次加入粉丝一起煮，粉丝吸尽大虾和黑椒的味道，大虾顿时成了配角呢！",
		"click_count": 21492,
		"title": "黑椒大虾炒粉丝",
		"rid": 1692,
		"share_count": 134,
		"str_date": "2016-10-11 10:39:00",
		"recipe_id": 37848,
		"group_id": 0,
		"locationId": null,
		"favorite_count": 2299,
		"favorite": "false",
		"makingTime": "20分钟"
	}, {
		"recipe_type": "00",
		"locationName": null,
		"image_url": "http://pic.daydaycook.com/production/images/20160811/d8437e1f-bb9c-4543-984a-fea55b8ad65d",
		"recommend_type": "1",
		"description": "用迷迭香烤羊排，让羊排不仅散发出肉质的香气，而且还伴着迷迭香的味道，有一种异域的感觉。法国人常以浪漫著称，就连一道迷迭香烤羊排，尽管做法简单，但味道却上佳，适合居家的你，品着红酒，吃着迷迭香烤羊排，今天来跟我们一起做起来吧。",
		"click_count": 13173,
		"title": "迷迭香烤羊排",
		"rid": 1691,
		"share_count": 91,
		"str_date": "2016-10-11 10:39:00",
		"recipe_id": 37646,
		"group_id": 0,
		"locationId": null,
		"favorite_count": 2128,
		"favorite": "false",
		"makingTime": "1小时"
	}, {
		"recipe_type": "00",
		"locationName": null,
		"image_url": "http://pic.daydaycook.com/production/images/20151130/06e1b08c-6ade-4146-9820-e9c76ea8a1cf",
		"recommend_type": "1",
		"description": "看过《爱情厨房》的人都会对影片中无处不在，味道令人惊叹的英式甜品Trifle充满好奇。Trifle是英国的传统甜品，特别之处就是将各种自己喜欢的水果和蛋糕、奶油美妙地组合在一起，每一勺都有多种滋味融合，惊喜无限。装在透明的容器中，多样食材绚丽地搭配也十分吸引眼球。\r\n",
		"click_count": 33878,
		"title": "英式布丁",
		"rid": 1690,
		"share_count": 159,
		"str_date": "2016-10-11 10:39:00",
		"recipe_id": 37181,
		"group_id": 0,
		"locationId": null,
		"favorite_count": 4359,
		"favorite": "false",
		"makingTime": "1.5小时"
	}]
}